perceval_gharchive/__init__.py
perceval_gharchive/backends/__init__.py
perceval_gharchive/backends/_version.py
perceval_gharchive/backends/gharchive.py
perceval_gharchive-0.1.1.dist-info/LICENSE
perceval_gharchive-0.1.1.dist-info/METADATA
perceval_gharchive-0.1.1.dist-info/WHEEL
perceval_gharchive-0.1.1.dist-info/RECORD
