Metadata-Version: 2.1
Name: perceval-gharchive
Version: 0.1.1
Summary: A GitHub Archive backend for GrimoireLab Perceval.
License: GPL-3.0 License
Author: wmeijer221
Author-email: me@wmeijer.com
Requires-Python: >=3.8.1,<4.0
Classifier: License :: Other/Proprietary License
Classifier: Programming Language :: Python :: 3
Classifier: Programming Language :: Python :: 3.9
Classifier: Programming Language :: Python :: 3.10
Classifier: Programming Language :: Python :: 3.11
Requires-Dist: logging (>=0.4.9.6,<0.5.0.0)
Requires-Dist: perceval (>=0.21.3,<0.22.0)
Requires-Dist: requests (>=2.28.2,<3.0.0)
